optimrl/__init__.py
optimrl/_version.py
optimrl/agents.py
optimrl/core.py
optimrl-1.0.1.dist-info/licenses/LICENSE
optimrl-1.0.1.dist-info/METADATA
optimrl-1.0.1.dist-info/WHEEL
optimrl-1.0.1.dist-info/top_level.txt
optimrl-1.0.1.dist-info/RECORD
